[
  {
    "日本語": "アジャン",
    "カラバル語": "aján",
    "IPA": "äd͡ʑä́n",
    "アラビア文字": "اجن",
    "語根": "jV́n",
    "語根+接辞": "a-jV́n",
    "同音異義語説明": null,
    "同音異義語+接辞": null,
    "補足": "禁忌の一つで、淫乱のことです。"
  },
  {
    "日本語": "アマン",
    "カラバル語": "amán",
    "IPA": "ämä́n",
    "アラビア文字": "امن",
    "語根": "mV́n",
    "語根+接辞": "a-mV́n",
    "同音異義語説明": null,
    "同音異義語+接辞": null,
    "補足": "禁忌の一つで、不適のことです。"
  },
  {
    "日本語": "アピラ",
    "カラバル語": "apïrà",
    "IPA": "äpɨrä̀",
    "アラビア文字": "اپر",
    "語根": "pïrV̀",
    "語根+接辞": "a-pïrV̀",
    "同音異義語説明": null,
    "同音異義語+接辞": null,
    "補足": "禁忌の一つで、過剰のことです。"
  },
  {
    "日本語": "アカダル",
    "カラバル語": "aqàdál",
    "IPA": "äqä̀dä́l",
    "アラビア文字": "اقدل",
    "語根": "qV̀d",
    "語根+接辞": "a-qV̀d-ál",
    "同音異義語説明": null,
    "同音異義語+接辞": null,
    "補足": "義務の一つで、喜捨のことです。"
  },
  {
    "日本語": "死ぬ",
    "カラバル語": "bábe",
    "IPA": "bä́bə",
    "アラビア文字": "بب",
    "語根": "bV́",
    "語根+接辞": "bV́-be",
    "同音異義語説明": null,
    "同音異義語+接辞": null,
    "補足": null
  },
  {
    "日本語": "暖かい",
    "カラバル語": "bàur",
    "IPA": "bä̀ʊr",
    "アラビア文字": "بور",
    "語根": "bV̀u",
    "語根+接辞": "bV̀u-r",
    "同音異義語説明": null,
    "同音異義語+接辞": null,
    "補足": null
  },
  {
    "日本語": "全ての",
    "カラバル語": "biār",
    "IPA": "bɪǟr",
    "アラビア文字": "بير",
    "語根": "biV̄",
    "語根+接辞": "biV̄-r",
    "同音異義語説明": null,
    "同音異義語+接辞": null,
    "補足": null
  },
  {
    "日本語": "海",
    "カラバル語": "bïlè",
    "IPA": "bɨlə̀",
    "アラビア文字": "بل",
    "語根": "bïlV̀",
    "語根+接辞": "bïlV̀",
    "同音異義語説明": null,
    "同音異義語+接辞": null,
    "補足": null
  },
  {
    "日本語": "歯",
    "カラバル語": "bïlí",
    "IPA": "bɨlɨ́",
    "アラビア文字": "بل",
    "語根": "bïlV́",
    "語根+接辞": "bïlV́",
    "同音異義語説明": null,
    "同音異義語+接辞": null,
    "補足": null
  },
  {
    "日本語": "孫/孫娘",
    "カラバル語": "bïmà/bïmè",
    "IPA": "bɨmä̀/bɨmə̀",
    "アラビア文字": "بم/بم",
    "語根": "bïmV̀",
    "語根+接辞": "bïmV̀",
    "同音異義語説明": null,
    "同音異義語+接辞": null,
    "補足": null
  },
  {
    "日本語": "王",
    "カラバル語": "bïmál",
    "IPA": "bɨmä́l",
    "アラビア文字": "بمل",
    "語根": "bïmV́l",
    "語根+接辞": "bïmV́l",
    "同音異義語説明": null,
    "同音異義語+接辞": null,
    "補足": null
  },
  {
    "日本語": "ビマウセ",
    "カラバル語": "bïmàuse",
    "IPA": "bɨmä̀ʊsə",
    "アラビア文字": "بموس",
    "語根": "bïmV̀use",
    "語根+接辞": "bïmV̀use",
    "同音異義語説明": null,
    "同音異義語+接辞": null,
    "補足": "禁忌の一つで、虚偽のことです。"
  },
  {
    "日本語": "鼻",
    "カラバル語": "bïmēir",
    "IPA": "bɨmə̄ɪr",
    "アラビア文字": "بمير",
    "語根": "bïmV̄ir",
    "語根+接辞": "bïmV̄ir",
    "同音異義語説明": null,
    "同音異義語+接辞": null,
    "補足": null
  },
  {
    "日本語": "尻尾",
    "カラバル語": "bïmì",
    "IPA": "bɨmɨ̀",
    "アラビア文字": "بم",
    "語根": "bïmV̀",
    "語根+接辞": "bïmV̀",
    "同音異義語説明": null,
    "同音異義語+接辞": null,
    "補足": null
  },
  {
    "日本語": "葉",
    "カラバル語": "bïmír",
    "IPA": "bɨmɨ́r",
    "アラビア文字": "بمر",
    "語根": "bïmV́r",
    "語根+接辞": "bïmV́r",
    "同音異義語説明": null,
    "同音異義語+接辞": null,
    "補足": null
  },
  {
    "日本語": "足",
    "カラバル語": "bïmò",
    "IPA": "bɨmɵ̀",
    "アラビア文字": "بم",
    "語根": "bïmV̀",
    "語根+接辞": "bïmV̀",
    "同音異義語説明": null,
    "同音異義語+接辞": null,
    "補足": null
  },
  {
    "日本語": "平地",
    "カラバル語": "bïrēsé",
    "IPA": "bɨrə̄sə́",
    "アラビア文字": "برس",
    "語根": "bïrV̄sé",
    "語根+接辞": "bïrV̄sé",
    "同音異義語説明": null,
    "同音異義語+接辞": null,
    "補足": null
  },
  {
    "日本語": 7,
    "カラバル語": "bïrï",
    "IPA": "bɨrɨ",
    "アラビア文字": "بر",
    "語根": "bïrï",
    "語根+接辞": "bïrï",
    "同音異義語説明": null,
    "同音異義語+接辞": null,
    "補足": null
  },
  {
    "日本語": 10,
    "カラバル語": "bìu",
    "IPA": "bɨ̀ʊ",
    "アラビア文字": "بو",
    "語根": "bìu",
    "語根+接辞": "bìu",
    "同音異義語説明": null,
    "同音異義語+接辞": null,
    "補足": null
  },
  {
    "日本語": "草",
    "カラバル語": "bíun",
    "IPA": "bɨ́ʊn",
    "アラビア文字": "بون",
    "語根": "bV́un",
    "語根+接辞": "bV́un",
    "同音異義語説明": null,
    "同音異義語+接辞": null,
    "補足": null
  },
  {
    "日本語": "あなた",
    "カラバル語": "sháu",
    "IPA": "ɕä́ʊ",
    "アラビア文字": "شو",
    "語根": "shV́",
    "語根+接辞": "shV́",
    "同音異義語説明": null,
    "同音異義語+接辞": null,
    "補足": null
  },
  {
    "日本語": "あなた達",
    "カラバル語": "sháuny",
    "IPA": "ɕä́ʊɲ",
    "アラビア文字": "شوڽ",
    "語根": "shV́uny",
    "語根+接辞": "shV́uny",
    "同音異義語説明": null,
    "同音異義語+接辞": null,
    "補足": null
  },
  {
    "日本語": "大きい",
    "カラバル語": "shàur",
    "IPA": "ɕä̀ʊr",
    "アラビア文字": "شور",
    "語根": "shV̀u",
    "語根+接辞": "shV̀u-r",
    "同音異義語説明": null,
    "同音異義語+接辞": null,
    "補足": null
  },
  {
    "日本語": "海岸",
    "カラバル語": "shèu",
    "IPA": "ɕə̀ʊ",
    "アラビア文字": "شو",
    "語根": "shV̀u",
    "語根+接辞": "shV̀u",
    "同音異義語説明": null,
    "同音異義語+接辞": null,
    "補足": null
  },
  {
    "日本語": "年",
    "カラバル語": "shiā",
    "IPA": "ɕɪǟ",
    "アラビア文字": "شي",
    "語根": "shiV̄",
    "語根+接辞": "shiV̄",
    "同音異義語説明": null,
    "同音異義語+接辞": null,
    "補足": null
  },
  {
    "日本語": "シアル",
    "カラバル語": "shiàl",
    "IPA": "ɕɪä̀l",
    "アラビア文字": "شيل",
    "語根": "shiV̀l",
    "語根+接辞": "shiV̀l",
    "同音異義語説明": null,
    "同音異義語+接辞": null,
    "補足": "義務の一つで、互助のことです。"
  },
  {
    "日本語": "猫",
    "カラバル語": "shïrïughe",
    "IPA": "ɕɨrɨʊʁə",
    "アラビア文字": "شروغ",
    "語根": "shïrVughe",
    "語根+接辞": "shïrVughe",
    "同音異義語説明": null,
    "同音異義語+接辞": null,
    "補足": null
  },
  {
    "日本語": "（厚みが）薄い",
    "カラバル語": "dāir",
    "IPA": "dǟɪr",
    "アラビア文字": "دير",
    "語根": "dV̄i",
    "語根+接辞": "dV̄i-r",
    "同音異義語説明": null,
    "同音異義語+接辞": null,
    "補足": null
  },
  {
    "日本語": "昼",
    "カラバル語": "dàu",
    "IPA": "dä̀ʊ",
    "アラビア文字": "دو",
    "語根": "dV̀u",
    "語根+接辞": "dV̀u",
    "同音異義語説明": null,
    "同音異義語+接辞": null,
    "補足": null
  },
  {
    "日本語": "眠る",
    "カラバル語": "daube",
    "IPA": "däʊbə",
    "アラビア文字": "دوب",
    "語根": "dVu",
    "語根+接辞": "dVu-be",
    "同音異義語説明": null,
    "同音異義語+接辞": null,
    "補足": null
  },
  {
    "日本語": "女",
    "カラバル語": "dēl",
    "IPA": "də̄l",
    "アラビア文字": "دل",
    "語根": "dV̄l",
    "語根+接辞": "dV̄l",
    "同音異義語説明": null,
    "同音異義語+接辞": null,
    "補足": null
  },
  {
    "日本語": "来る",
    "カラバル語": "dïlàibe",
    "IPA": "dɨlä̀ɪbə",
    "アラビア文字": "دليب",
    "語根": "dVlV̀i",
    "語根+接辞": "dVlV̀i-be",
    "同音異義語説明": null,
    "同音異義語+接辞": null,
    "補足": null
  },
  {
    "日本語": "首",
    "カラバル語": "dïlèu",
    "IPA": "dɨlə̀ʊ",
    "アラビア文字": "دلو",
    "語根": "dïlV̀u",
    "語根+接辞": "dïlV̀u",
    "同音異義語説明": null,
    "同音異義語+接辞": null,
    "補足": null
  },
  {
    "日本語": "山",
    "カラバル語": "dïnē",
    "IPA": "dɨnə̄",
    "アラビア文字": "دن",
    "語根": "dïnV̄",
    "語根+接辞": "dïnV̄",
    "同音異義語説明": null,
    "同音異義語+接辞": null,
    "補足": null
  },
  {
    "日本語": "太陽",
    "カラバル語": "dïnil",
    "IPA": "dɨnɪl",
    "アラビア文字": "دنيل",
    "語根": "dïnVl",
    "語根+接辞": "dïnVl",
    "同音異義語説明": null,
    "同音異義語+接辞": null,
    "補足": null
  },
  {
    "日本語": 9,
    "カラバル語": "dïrím",
    "IPA": "dɨrɨ́m",
    "アラビア文字": "درم",
    "語根": "dïrím",
    "語根+接辞": "dïrím",
    "同音異義語説明": null,
    "同音異義語+接辞": null,
    "補足": null
  },
  {
    "日本語": "いつ",
    "カラバル語": "dóye",
    "IPA": "dɵ́jə",
    "アラビア文字": "دي",
    "語根": "dó",
    "語根+接辞": "dó-ye",
    "同音異義語説明": null,
    "同音異義語+接辞": null,
    "補足": null
  },
  {
    "日本語": "妻",
    "カラバル語": "dón",
    "IPA": "dɵ́n",
    "アラビア文字": "دن",
    "語根": "dV́n",
    "語根+接辞": "dV́n",
    "同音異義語説明": null,
    "同音異義語+接辞": null,
    "補足": null
  },
  {
    "日本語": "魚",
    "カラバル語": "dou",
    "IPA": "dɵʊ",
    "アラビア文字": "دو",
    "語根": "dVu",
    "語根+接辞": "dVu",
    "同音異義語説明": null,
    "同音異義語+接辞": null,
    "補足": null
  },
  {
    "日本語": "口",
    "カラバル語": "drēl",
    "IPA": "drə̄l",
    "アラビア文字": "درل",
    "語根": "dïrV̄l",
    "語根+接辞": "dïrV̄l",
    "同音異義語説明": null,
    "同音異義語+接辞": null,
    "補足": null
  },
  {
    "日本語": "黒",
    "カラバル語": "duà",
    "IPA": "dʊä̀",
    "アラビア文字": "دو",
    "語根": "duV̀",
    "語根+接辞": "duV̀",
    "同音異義語説明": "「長い」との区別",
    "同音異義語+接辞": "sè-duàr",
    "補足": null
  },
  {
    "日本語": "長い",
    "カラバル語": "duàr",
    "IPA": "dʊä̀r",
    "アラビア文字": "دور",
    "語根": "duV̀",
    "語根+接辞": "duV̀-r",
    "同音異義語説明": null,
    "同音異義語+接辞": null,
    "補足": null
  },
  {
    "日本語": "手",
    "カラバル語": "duì",
    "IPA": "dʊɨ̀",
    "アラビア文字": "دو",
    "語根": "duV̀",
    "語根+接辞": "duV̀",
    "同音異義語説明": null,
    "同音異義語+接辞": null,
    "補足": null
  },
  {
    "日本語": "彼",
    "カラバル語": "já",
    "IPA": "d͡ʑä́",
    "アラビア文字": "ج",
    "語根": "jV́",
    "語根+接辞": "jV́",
    "同音異義語説明": null,
    "同音異義語+接辞": null,
    "補足": null
  },
  {
    "日本語": "壊す",
    "カラバル語": "jabe",
    "IPA": "d͡ʑäbə",
    "アラビア文字": "جب",
    "語根": "jV",
    "語根+接辞": "jV-be",
    "同音異義語説明": null,
    "同音異義語+接辞": null,
    "補足": null
  },
  {
    "日本語": "戦争",
    "カラバル語": "zàgā",
    "IPA": "d͡zä̀gǟ",
    "アラビア文字": "زگ",
    "語根": "zV̀gV̄",
    "語根+接辞": "zV̀gV̄",
    "同音異義語説明": null,
    "同音異義語+接辞": null,
    "補足": null
  },
  {
    "日本語": "首都",
    "カラバル語": "zāggài",
    "IPA": "d͡zǟɢä̀ɪ",
    "アラビア文字": "زڠي",
    "語根": "zV̄ggV̀i",
    "語根+接辞": "zV̄ggV̀i",
    "同音異義語説明": null,
    "同音異義語+接辞": null,
    "補足": null
  },
  {
    "日本語": "祖国",
    "カラバル語": "zàijuāy",
    "IPA": "d͡zä̀ɪd͡ʑʊǟj",
    "アラビア文字": "زيجوي",
    "語根": "zV̀ijuV̄y",
    "語根+接辞": "zV̀ijuV̄y",
    "同音異義語説明": null,
    "同音異義語+接辞": null,
    "補足": null
  },
  {
    "日本語": "自由",
    "カラバル語": "zāighia",
    "IPA": "d͡zǟɪʁɪä",
    "アラビア文字": "زيغي",
    "語根": "zV̄ighiV",
    "語根+接辞": "zV̄ighiV",
    "同音異義語説明": null,
    "同音異義語+接辞": null,
    "補足": null
  },
  {
    "日本語": "彼ら",
    "カラバル語": "jány",
    "IPA": "d͡ʑä́ɲ",
    "アラビア文字": "جڽ",
    "語根": "jV́ny",
    "語根+接辞": "jV́ny",
    "同音異義語説明": null,
    "同音異義語+接辞": null,
    "補足": null
  },
  {
    "日本語": "見る",
    "カラバル語": "záube",
    "IPA": "d͡zä́ʊbə",
    "アラビア文字": "زوب",
    "語根": "zV́u",
    "語根+接辞": "zV́u-be",
    "同音異義語説明": null,
    "同音異義語+接辞": null,
    "補足": null
  },
  {
    "日本語": "新しい",
    "カラバル語": "jàur",
    "IPA": "d͡ʑä̀ʊr",
    "アラビア文字": "جور",
    "語根": "jV̀u",
    "語根+接辞": "jV̀u-r",
    "同音異義語説明": null,
    "同音異義語+接辞": null,
    "補足": null
  },
  {
    "日本語": "地面",
    "カラバル語": "jè",
    "IPA": "d͡ʑə̀",
    "アラビア文字": "ج",
    "語根": "jV̀",
    "語根+接辞": "jV̀",
    "同音異義語説明": null,
    "同音異義語+接辞": null,
    "補足": null
  },
  {
    "日本語": "氷",
    "カラバル語": "zēu",
    "IPA": "d͡zə̄ʊ",
    "アラビア文字": "زو",
    "語根": "zV̄u",
    "語根+接辞": "zV̄u",
    "同音異義語説明": null,
    "同音異義語+接辞": null,
    "補足": null
  },
  {
    "日本語": "夜",
    "カラバル語": "ziāy",
    "IPA": "d͡zɪǟj",
    "アラビア文字": "زيي",
    "語根": "ziV̄y",
    "語根+接辞": "ziV̄y",
    "同音異義語説明": null,
    "同音異義語+接辞": null,
    "補足": null
  },
  {
    "日本語": "兄",
    "カラバル語": "zïlá",
    "IPA": "d͡zɨlä́",
    "アラビア文字": "زل",
    "語根": "zïlV́",
    "語根+接辞": "zïlV́",
    "同音異義語説明": null,
    "同音異義語+接辞": null,
    "補足": null
  },
  {
    "日本語": "ジレイ",
    "カラバル語": "jìlé",
    "IPA": "d͡ʑɨ̀lə́",
    "アラビア文字": "جل",
    "語根": "jV̀lé",
    "語根+接辞": "jV̀lé",
    "同音異義語説明": null,
    "同音異義語+接辞": null,
    "補足": "礼拝の呼びかけです。"
  },
  {
    "日本語": "空",
    "カラバル語": "zïliè",
    "IPA": "d͡zɨlɪə̀",
    "アラビア文字": "زلي",
    "語根": "zïliV̀",
    "語根+接辞": "zïliV̀",
    "同音異義語説明": null,
    "同音異義語+接辞": null,
    "補足": null
  },
  {
    "日本語": "石",
    "カラバル語": "zïlïyï",
    "IPA": "d͡zɨlɨjɨ",
    "アラビア文字": "زلي",
    "語根": "zïlVyV",
    "語根+接辞": "zïlVyV",
    "同音異義語説明": null,
    "同音異義語+接辞": null,
    "補足": null
  },
  {
    "日本語": "皮",
    "カラバル語": "jïròung",
    "IPA": "d͡ʑɨrɵ̀ʊŋ",
    "アラビア文字": "جروﯓ",
    "語根": "jïrV̀ung",
    "語根+接辞": "jïrV̀ung",
    "同音異義語説明": null,
    "同音異義語+接辞": null,
    "補足": null
  },
  {
    "日本語": "舌",
    "カラバル語": "jïruè",
    "IPA": "d͡ʑɨrʊə̀",
    "アラビア文字": "جرو",
    "語根": "jïruV̀",
    "語根+接辞": "jïruV̀",
    "同音異義語説明": null,
    "同音異義語+接辞": null,
    "補足": null
  },
  {
    "日本語": 2,
    "カラバル語": "jìu",
    "IPA": "d͡ʑɨ̀ʊ",
    "アラビア文字": "جو",
    "語根": "jìu",
    "語根+接辞": "jìu",
    "同音異義語説明": null,
    "同音異義語+接辞": null,
    "補足": null
  },
  {
    "日本語": "角",
    "カラバル語": "zíur",
    "IPA": "d͡zɨ́ʊr",
    "アラビア文字": "زور",
    "語根": "zV́ur",
    "語根+接辞": "zV́ur",
    "同音異義語説明": null,
    "同音異義語+接辞": null,
    "補足": null
  },
  {
    "日本語": "虫",
    "カラバル語": "jól",
    "IPA": "d͡ʑɵ́l",
    "アラビア文字": "جل",
    "語根": "jV́l",
    "語根+接辞": "jV́l",
    "同音異義語説明": null,
    "同音異義語+接辞": null,
    "補足": null
  },
  {
    "日本語": "～するとき",
    "カラバル語": "zórei",
    "IPA": "d͡zɵ́rəɪ",
    "アラビア文字": "زري",
    "語根": "zór",
    "語根+接辞": "zór-ei",
    "同音異義語説明": null,
    "同音異義語+接辞": null,
    "補足": null
  },
  {
    "日本語": "泳ぐ",
    "カラバル語": "juabe",
    "IPA": "d͡ʑʊäbə",
    "アラビア文字": "جوب",
    "語根": "juV",
    "語根+接辞": "juV-be",
    "同音異義語説明": null,
    "同音異義語+接辞": null,
    "補足": null
  },
  {
    "日本語": "頭",
    "カラバル語": "juèn",
    "IPA": "d͡ʑʊə̀n",
    "アラビア文字": "جون",
    "語根": "juV̀n",
    "語根+接辞": "juV̀n",
    "同音異義語説明": null,
    "同音異義語+接辞": null,
    "補足": null
  },
  {
    "日本語": "ガジェン・ユワ",
    "カラバル語": "gájén yuā",
    "IPA": "gä́d͡ʑə́n jʊǟ",
    "アラビア文字": "گجن يو",
    "語根": "gV́j yuV̄",
    "語根+接辞": "gV́j-én yuV̄",
    "同音異義語説明": null,
    "同音異義語+接辞": null,
    "補足": "禁忌の一つで、三悪（殺し・盗み・脅し）のことです。"
  },
  {
    "日本語": "男",
    "カラバル語": "gār",
    "IPA": "gǟr",
    "アラビア文字": "گر",
    "語根": "gV̄r",
    "語根+接辞": "gV̄r",
    "同音異義語説明": null,
    "同音異義語+接辞": null,
    "補足": null
  },
  {
    "日本語": "夫",
    "カラバル語": "gàve",
    "IPA": "gä̀βə",
    "アラビア文字": "گڤ",
    "語根": "gV̀ve",
    "語根+接辞": "gV̀ve",
    "同音異義語説明": null,
    "同音異義語+接辞": null,
    "補足": null
  },
  {
    "日本語": "三尾の狐",
    "カラバル語": "géjéné",
    "IPA": "gə́d͡ʑə́nə́",
    "アラビア文字": "گجن",
    "語根": "gV́jV́né",
    "語根+接辞": "gV́jV́né",
    "同音異義語説明": null,
    "同音異義語+接辞": null,
    "補足": "ディラル派の神使です。"
  },
  {
    "日本語": "母",
    "カラバル語": "ggèun",
    "IPA": "ɢə̀ʊn",
    "アラビア文字": "ڠون",
    "語根": "ggV̀un",
    "語根+接辞": "ggV̀un",
    "同音異義語説明": null,
    "同音異義語+接辞": null,
    "補足": null
  },
  {
    "日本語": "羽根、翼",
    "カラバル語": "gī",
    "IPA": "gɨ̄",
    "アラビア文字": "گ",
    "語根": "gV̄",
    "語根+接辞": "gV̄",
    "同音異義語説明": null,
    "同音異義語+接辞": null,
    "補足": null
  },
  {
    "日本語": 3,
    "カラバル語": "gíje",
    "IPA": "gɨ́d͡ʑə",
    "アラビア文字": "گج",
    "語根": "gíje",
    "語根+接辞": "gíje",
    "同音異義語説明": null,
    "同音異義語+接辞": null,
    "補足": null
  },
  {
    "日本語": "遠い",
    "カラバル語": "gïlāir",
    "IPA": "gɨlǟɪr",
    "アラビア文字": "گلير",
    "語根": "gVlV̄i",
    "語根+接辞": "gVlV̄i-r",
    "同音異義語説明": null,
    "同音異義語+接辞": null,
    "補足": null
  },
  {
    "日本語": "髪",
    "カラバル語": "gïlī",
    "IPA": "gɨlɨ̄",
    "アラビア文字": "گل",
    "語根": "gïlV̄",
    "語根+接辞": "gïlV̄",
    "同音異義語説明": null,
    "同音異義語+接辞": null,
    "補足": null
  },
  {
    "日本語": "雨",
    "カラバル語": "gïnē",
    "IPA": "gɨnə̄",
    "アラビア文字": "گن",
    "語根": "gïnV̄",
    "語根+接辞": "gïnV̄",
    "同音異義語説明": null,
    "同音異義語+接辞": null,
    "補足": null
  },
  {
    "日本語": "犬",
    "カラバル語": "gïnīl",
    "IPA": "gɨnɨ̄l",
    "アラビア文字": "گنل",
    "語根": "gïnV̄l",
    "語根+接辞": "gïnV̄l",
    "同音異義語説明": null,
    "同音異義語+接辞": null,
    "補足": null
  },
  {
    "日本語": "0、無",
    "カラバル語": "gïnuï",
    "IPA": "gɨnʊɨ",
    "アラビア文字": "گنو",
    "語根": "gïnuï",
    "語根+接辞": "gïnuï",
    "同音異義語説明": null,
    "同音異義語+接辞": null,
    "補足": null
  },
  {
    "日本語": "土",
    "カラバル語": "gïrèun",
    "IPA": "gɨrə̀ʊn",
    "アラビア文字": "گرون",
    "語根": "gïrV̀un",
    "語根+接辞": "gïrV̀un",
    "同音異義語説明": null,
    "同音異義語+接辞": null,
    "補足": null
  },
  {
    "日本語": "星",
    "カラバル語": "gïrín",
    "IPA": "gɨrɨ́n",
    "アラビア文字": "گرن",
    "語根": "gïrV́n",
    "語根+接辞": "gïrV́n",
    "同音異義語説明": null,
    "同音異義語+接辞": null,
    "補足": null
  },
  {
    "日本語": "しかし",
    "カラバル語": "ggo",
    "IPA": "ɢɵ",
    "アラビア文字": "ڠ",
    "語根": "ggo",
    "語根+接辞": "ggo",
    "同音異義語説明": null,
    "同音異義語+接辞": null,
    "補足": null
  },
  {
    "日本語": "学ぶ",
    "カラバル語": "gguābe",
    "IPA": "ɢʊǟbə",
    "アラビア文字": "ڠوب",
    "語根": "gguV̄",
    "語根+接辞": "gguV̄-be",
    "同音異義語説明": null,
    "同音異義語+接辞": null,
    "補足": null
  },
  {
    "日本語": "真実",
    "カラバル語": "gguàhà",
    "IPA": "ɢʊä̀ɦä̀",
    "アラビア文字": "ڠوع",
    "語根": "gguV̀hV̀",
    "語根+接辞": "gguV̀hV̀",
    "同音異義語説明": null,
    "同音異義語+接辞": null,
    "補足": null
  },
  {
    "日本語": "戦う",
    "カラバル語": "háibe",
    "IPA": "ɦä́ɪbə",
    "アラビア文字": "عيب",
    "語根": "hV́i",
    "語根+接辞": "hV́i-be",
    "同音異義語説明": null,
    "同音異義語+接辞": null,
    "補足": null
  },
  {
    "日本語": "小さい",
    "カラバル語": "hhāir",
    "IPA": "hǟɪr",
    "アラビア文字": "حير",
    "語根": "hhV̄i",
    "語根+接辞": "hhV̄i-r",
    "同音異義語説明": null,
    "同音異義語+接辞": null,
    "補足": null
  },
  {
    "日本語": "ハリア",
    "カラバル語": "hhàriá",
    "IPA": "hä̀rɪä́",
    "アラビア文字": "حري",
    "語根": "hhV̀riV́",
    "語根+接辞": "hhV̀riV́",
    "同音異義語説明": null,
    "同音異義語+接辞": null,
    "補足": "義務の一つで、水平のことです。"
  },
  {
    "日本語": "讃える",
    "カラバル語": "hhàube",
    "IPA": "hä̀ʊbə",
    "アラビア文字": "حوب",
    "語根": "hhV̀u",
    "語根+接辞": "hhV̀u-be",
    "同音異義語説明": null,
    "同音異義語+接辞": null,
    "補足": null
  },
  {
    "日本語": "飲む",
    "カラバル語": "haube",
    "IPA": "ɦäʊbə",
    "アラビア文字": "عوب",
    "語根": "hVu",
    "語根+接辞": "hVu-be",
    "同音異義語説明": null,
    "同音異義語+接辞": null,
    "補足": null
  },
  {
    "日本語": "歌う",
    "カラバル語": "hàube",
    "IPA": "ɦä̀ʊbə",
    "アラビア文字": "عوب",
    "語根": "hV̀u",
    "語根+接辞": "hV̀u-be",
    "同音異義語説明": null,
    "同音異義語+接辞": null,
    "補足": null
  },
  {
    "日本語": "愛する",
    "カラバル語": "hàube",
    "IPA": "ɦä̀ʊbə",
    "アラビア文字": "عوب",
    "語根": "hV̀u",
    "語根+接辞": "hV̀u-be",
    "同音異義語説明": "「歌う」との区別",
    "同音異義語+接辞": "sè-hV̀u-be",
    "補足": null
  },
  {
    "日本語": "なぜなら",
    "カラバル語": "ho",
    "IPA": "ɦɵ",
    "アラビア文字": "ع",
    "語根": "ho",
    "語根+接辞": "ho",
    "同音異義語説明": null,
    "同音異義語+接辞": null,
    "補足": null
  },
  {
    "日本語": "果実、実",
    "カラバル語": "hóun",
    "IPA": "ɦɵ́ʊn",
    "アラビア文字": "عون",
    "語根": "hV́un",
    "語根+接辞": "hV́un",
    "同音異義語説明": null,
    "同音異義語+接辞": null,
    "補足": null
  },
  {
    "日本語": "歩く",
    "カラバル語": "hhuábe",
    "IPA": "hʊä́bə",
    "アラビア文字": "حوب",
    "語根": "hhuV́",
    "語根+接辞": "hhuV́-be",
    "同音異義語説明": null,
    "同音異義語+接辞": null,
    "補足": null
  },
  {
    "日本語": "立つ",
    "カラバル語": "yábe",
    "IPA": "jä́bə",
    "アラビア文字": "يب",
    "語根": "yV́",
    "語根+接辞": "yV́-be",
    "同音異義語説明": null,
    "同音異義語+接辞": null,
    "補足": null
  },
  {
    "日本語": "ヤイヴァ",
    "カラバル語": "yáivá",
    "IPA": "jä́ɪβä́",
    "アラビア文字": "ييڤ",
    "語根": "yV́ivV́",
    "語根+接辞": "yV́ivV́",
    "同音異義語説明": null,
    "同音異義語+接辞": null,
    "補足": "義務の一つで、礼拝のことです。"
  },
  {
    "日本語": "家",
    "カラバル語": "yàng",
    "IPA": "jä̀ŋ",
    "アラビア文字": "يﯓ",
    "語根": "yV̀ng",
    "語根+接辞": "yV̀ng",
    "同音異義語説明": null,
    "同音異義語+接辞": null,
    "補足": null
  },
  {
    "日本語": "近い",
    "カラバル語": "yàr",
    "IPA": "jä̀r",
    "アラビア文字": "ير",
    "語根": "yV̀",
    "語根+接辞": "yV̀-r",
    "同音異義語説明": null,
    "同音異義語+接辞": null,
    "補足": null
  },
  {
    "日本語": "独立",
    "カラバル語": "yāsáu",
    "IPA": "jǟsä́ʊ",
    "アラビア文字": "يسو",
    "語根": "yV̄sV́u",
    "語根+接辞": "yV̄sV́u",
    "同音異義語説明": null,
    "同音異義語+接辞": null,
    "補足": null
  },
  {
    "日本語": "結ぶ",
    "カラバル語": "yàube",
    "IPA": "jä̀ʊbə",
    "アラビア文字": "يوب",
    "語根": "yV̀u",
    "語根+接辞": "yV̀u-be",
    "同音異義語説明": "「恐れる」との区別",
    "同音異義語+接辞": "sè-yV̀u-be",
    "補足": null
  },
  {
    "日本語": "恐れる",
    "カラバル語": "yàube",
    "IPA": "jä̀ʊbə",
    "アラビア文字": "يوب",
    "語根": "yV̀u",
    "語根+接辞": "yV̀u-be",
    "同音異義語説明": null,
    "同音異義語+接辞": null,
    "補足": null
  },
  {
    "日本語": "（幅が）広い",
    "カラバル語": "yiār",
    "IPA": "jɪǟr",
    "アラビア文字": "يير",
    "語根": "yiV̄",
    "語根+接辞": "yiV̄-r",
    "同音異義語説明": null,
    "同音異義語+接辞": null,
    "補足": null
  },
  {
    "日本語": "イディア",
    "カラバル語": "yìdia",
    "IPA": "jɨ̀dɪä",
    "アラビア文字": "يدي",
    "語根": "diV",
    "語根+接辞": "yì-diV",
    "同音異義語説明": null,
    "同音異義語+接辞": null,
    "補足": "子供に与えるお年玉です。"
  },
  {
    "日本語": "イサル",
    "カラバル語": "yísál",
    "IPA": "jɨ́sä́l",
    "アラビア文字": "يسل",
    "語根": "yV́s",
    "語根+接辞": "yV́s-ál",
    "同音異義語説明": null,
    "同音異義語+接辞": null,
    "補足": "パテイの受難の追体験を意味します。"
  },
  {
    "日本語": "イウハ",
    "カラバル語": "yíuhha",
    "IPA": "jɨ́ʊhä",
    "アラビア文字": "يوح",
    "語根": "hhV",
    "語根+接辞": "yíu-hhV",
    "同音異義語説明": null,
    "同音異義語+接辞": null,
    "補足": "信仰告白を意味します。"
  },
  {
    "日本語": "座る",
    "カラバル語": "yuábe",
    "IPA": "jʊä́bə",
    "アラビア文字": "يوب",
    "語根": "yuV́",
    "語根+接辞": "yuV́-be",
    "同音異義語説明": null,
    "同音異義語+接辞": null,
    "補足": null
  },
  {
    "日本語": "悪い",
    "カラバル語": "yuār",
    "IPA": "jʊǟr",
    "アラビア文字": "يور",
    "語根": "yuV̄",
    "語根+接辞": "yuV̄-r",
    "同音異義語説明": null,
    "同音異義語+接辞": null,
    "補足": null
  },
  {
    "日本語": "ユワサイ",
    "カラバル語": "yuāsài",
    "IPA": "jʊǟsä̀ɪ",
    "アラビア文字": "يوسي",
    "語根": "yuV̄sV̀i",
    "語根+接辞": "yuV̄sV̀i",
    "同音異義語説明": null,
    "同音異義語+接辞": null,
    "補足": "悪学を意味します。"
  },
  {
    "日本語": "食べる",
    "カラバル語": "kàibe",
    "IPA": "kä̀ɪbə",
    "アラビア文字": "كيب",
    "語根": "kV̀i",
    "語根+接辞": "kV̀i-be",
    "同音異義語説明": null,
    "同音異義語+接辞": null,
    "補足": null
  },
  {
    "日本語": "胸",
    "カラバル語": "kē",
    "IPA": "kə̄",
    "アラビア文字": "ك",
    "語根": "kV̄",
    "語根+接辞": "kV̄",
    "同音異義語説明": null,
    "同音異義語+接辞": null,
    "補足": null
  },
  {
    "日本語": "（幅が）狭い",
    "カラバル語": "kiār",
    "IPA": "kɪǟr",
    "アラビア文字": "كير",
    "語根": "kiV̄",
    "語根+接辞": "kiV̄-r",
    "同音異義語説明": null,
    "同音異義語+接辞": null,
    "補足": null
  },
  {
    "日本語": 1000,
    "カラバル語": "kïlì",
    "IPA": "kɨlɨ̀",
    "アラビア文字": "كل",
    "語根": "kïlì",
    "語根+接辞": "kïlì",
    "同音異義語説明": null,
    "同音異義語+接辞": null,
    "補足": null
  },
  {
    "日本語": "名前",
    "カラバル語": "kïliāng",
    "IPA": "kɨlɪǟŋ",
    "アラビア文字": "كليﯓ",
    "語根": "kïliV̄ng",
    "語根+接辞": "kïliV̄ng",
    "同音異義語説明": null,
    "同音異義語+接辞": null,
    "補足": null
  },
  {
    "日本語": "得る",
    "カラバル語": "kuàbe",
    "IPA": "kʊä̀bə",
    "アラビア文字": "كوب",
    "語根": "kuV̀",
    "語根+接辞": "kuV̀-be",
    "同音異義語説明": null,
    "同音異義語+接辞": null,
    "補足": null
  },
  {
    "日本語": "水",
    "カラバル語": "kuēr",
    "IPA": "kʊə̄r",
    "アラビア文字": "كور",
    "語根": "kuV̄r",
    "語根+接辞": "kuV̄r",
    "同音異義語説明": null,
    "同音異義語+接辞": null,
    "補足": null
  },
  {
    "日本語": "教導",
    "カラバル語": "kuīshe",
    "IPA": "kʊɨ̄ɕə",
    "アラビア文字": "كوش",
    "語根": "kuV̄she",
    "語根+接辞": "kuV̄she",
    "同音異義語説明": null,
    "同音異義語+接辞": null,
    "補足": null
  },
  {
    "日本語": "いいえ",
    "カラバル語": "kuo",
    "IPA": "kʊɵ",
    "アラビア文字": "كو",
    "語根": "kuo",
    "語根+接辞": "kuo",
    "同音異義語説明": null,
    "同音異義語+接辞": null,
    "補足": null
  },
  {
    "日本語": "平和",
    "カラバル語": "lāiduá",
    "IPA": "lǟɪdʊä́",
    "アラビア文字": "ليدو",
    "語根": "lV̄iduá",
    "語根+接辞": "lV̄iduá",
    "同音異義語説明": null,
    "同音異義語+接辞": null,
    "補足": null
  },
  {
    "日本語": "良い",
    "カラバル語": "lāir",
    "IPA": "lǟɪr",
    "アラビア文字": "لير",
    "語根": "lV̄i",
    "語根+接辞": "lV̄i-r",
    "同音異義語説明": null,
    "同音異義語+接辞": null,
    "補足": null
  },
  {
    "日本語": "本当の、真の",
    "カラバル語": "hlàir",
    "IPA": "l̥ä̀ɪr",
    "アラビア文字": "هلير",
    "語根": "hlV̀i",
    "語根+接辞": "hlV̀i-r",
    "同音異義語説明": null,
    "同音異義語+接辞": null,
    "補足": null
  },
  {
    "日本語": "短い",
    "カラバル語": "hlāir",
    "IPA": "l̥ǟɪr",
    "アラビア文字": "هلير",
    "語根": "hlV̄i",
    "語根+接辞": "hlV̄i-r",
    "同音異義語説明": null,
    "同音異義語+接辞": null,
    "補足": null
  },
  {
    "日本語": "ラツワ",
    "カラバル語": "làcuá",
    "IPA": "lä̀t͡sʊä́",
    "アラビア文字": "لڃو",
    "語根": "lV̀cuV́",
    "語根+接辞": "lV̀cuV́",
    "同音異義語説明": null,
    "同音異義語+接辞": null,
    "補足": "義務の一つで、巡礼のことです。"
  },
  {
    "日本語": "赤",
    "カラバル語": "hlàu",
    "IPA": "l̥ä̀ʊ",
    "アラビア文字": "هلو",
    "語根": "hlV̀u",
    "語根+接辞": "hlV̀u",
    "同音異義語説明": null,
    "同音異義語+接辞": null,
    "補足": null
  },
  {
    "日本語": "涼しい",
    "カラバル語": "làunár",
    "IPA": "lä̀ʊnä́r",
    "アラビア文字": "لونر",
    "語根": "lV̀un",
    "語根+接辞": "lV̀un-ár",
    "同音異義語説明": null,
    "同音異義語+接辞": null,
    "補足": null
  },
  {
    "日本語": "黄色",
    "カラバル語": "liā",
    "IPA": "lɪǟ",
    "アラビア文字": "لي",
    "語根": "liV̄",
    "語根+接辞": "liV̄",
    "同音異義語説明": null,
    "同音異義語+接辞": null,
    "補足": null
  },
  {
    "日本語": "動物",
    "カラバル語": "lïyāun",
    "IPA": "lɨjǟʊn",
    "アラビア文字": "ليون",
    "語根": "lïyV̄un",
    "語根+接辞": "lïyV̄un",
    "同音異義語説明": null,
    "同音異義語+接辞": null,
    "補足": null
  },
  {
    "日本語": "これ（近くのもの）",
    "カラバル語": "líl",
    "IPA": "lɨ́l",
    "アラビア文字": "لل",
    "語根": "lV́l",
    "語根+接辞": "lV́l",
    "同音異義語説明": null,
    "同音異義語+接辞": null,
    "補足": null
  },
  {
    "日本語": "フリハル",
    "カラバル語": "hlïxàl",
    "IPA": "l̥ɨχä̀l",
    "アラビア文字": "هلخل",
    "語根": "xV̀l",
    "語根+接辞": "hlï-xV̀l",
    "同音異義語説明": null,
    "同音異義語+接辞": null,
    "補足": "義務（すべきこと）を指します。"
  },
  {
    "日本語": "与える",
    "カラバル語": "hluabe",
    "IPA": "l̥ʊäbə",
    "アラビア文字": "هلوب",
    "語根": "hluV",
    "語根+接辞": "hluV-be",
    "同音異義語説明": null,
    "同音異義語+接辞": null,
    "補足": null
  },
  {
    "日本語": "雲",
    "カラバル語": "luē",
    "IPA": "lʊə̄",
    "アラビア文字": "لو",
    "語根": "luV̄",
    "語根+接辞": "luV̄",
    "同音異義語説明": null,
    "同音異義語+接辞": null,
    "補足": null
  },
  {
    "日本語": "どのように",
    "カラバル語": "luóye",
    "IPA": "lʊɵ́jə",
    "アラビア文字": "لوي",
    "語根": "luó",
    "語根+接辞": "luó-ye",
    "同音異義語説明": null,
    "同音異義語+接辞": null,
    "補足": null
  },
  {
    "日本語": "なぜ",
    "カラバル語": "luonei",
    "IPA": "lʊɵnəɪ",
    "アラビア文字": "لوني",
    "語根": "luon",
    "語根+接辞": "luon-ei",
    "同音異義語説明": null,
    "同音異義語+接辞": null,
    "補足": null
  },
  {
    "日本語": "聞く",
    "カラバル語": "mábe",
    "IPA": "mä́bə",
    "アラビア文字": "مب",
    "語根": "mV́",
    "語根+接辞": "mV́-be",
    "同音異義語説明": null,
    "同音異義語+接辞": null,
    "補足": null
  },
  {
    "日本語": "マーシェ",
    "カラバル語": "māshe",
    "IPA": "mǟɕə",
    "アラビア文字": "مش",
    "語根": "mV̄she",
    "語根+接辞": "mV̄she",
    "同音異義語説明": null,
    "同音異義語+接辞": null,
    "補足": "義務の一つで、慈愛のことです。"
  },
  {
    "日本語": "マガセ",
    "カラバル語": "magáse",
    "IPA": "mägä́sə",
    "アラビア文字": "مگس",
    "語根": "mVgV́se",
    "語根+接辞": "mVgV́se",
    "同音異義語説明": null,
    "同音異義語+接辞": null,
    "補足": "旅人に与えられる称号です。"
  },
  {
    "日本語": "乾いた",
    "カラバル語": "màir",
    "IPA": "mä̀ɪr",
    "アラビア文字": "مير",
    "語根": "mV̀i",
    "語根+接辞": "mV̀i-r",
    "同音異義語説明": null,
    "同音異義語+接辞": null,
    "補足": null
  },
  {
    "日本語": "都市",
    "カラバル語": "hmàká",
    "IPA": "m̥ä̀kä́",
    "アラビア文字": "همك",
    "語根": "hmV̀kV́",
    "語根+接辞": "hmV̀kV́",
    "同音異義語説明": null,
    "同音異義語+接辞": null,
    "補足": null
  },
  {
    "日本語": "ママール",
    "カラバル語": "mámāl",
    "IPA": "mä́mǟl",
    "アラビア文字": "ممل",
    "語根": "mV́mV̄l",
    "語根+接辞": "mV́mV̄l",
    "同音異義語説明": null,
    "同音異義語+接辞": null,
    "補足": "デーツの入ったバタークッキーです。"
  },
  {
    "日本語": "フマタ",
    "カラバル語": "hmáta",
    "IPA": "m̥ä́tä",
    "アラビア文字": "همت",
    "語根": "hmV́ta",
    "語根+接辞": "hmV́ta",
    "同音異義語説明": null,
    "同音異義語+接辞": null,
    "補足": "禁忌の一つで、食汚のことです。"
  },
  {
    "日本語": "姉",
    "カラバル語": "hmeize",
    "IPA": "m̥əɪd͡zə",
    "アラビア文字": "هميز",
    "語根": "hmVize",
    "語根+接辞": "hmVize",
    "同音異義語説明": null,
    "同音異義語+接辞": null,
    "補足": null
  },
  {
    "日本語": "月",
    "カラバル語": "hmí",
    "IPA": "m̥ɨ́",
    "アラビア文字": "هم",
    "語根": "hmV́",
    "語根+接辞": "hmV́",
    "同音異義語説明": null,
    "同音異義語+接辞": null,
    "補足": null
  },
  {
    "日本語": "いる、ある",
    "カラバル語": "miábe",
    "IPA": "mɪä́bə",
    "アラビア文字": "ميب",
    "語根": "miV́",
    "語根+接辞": "miV́-be",
    "同音異義語説明": null,
    "同音異義語+接辞": null,
    "補足": null
  },
  {
    "日本語": "切る",
    "カラバル語": "hmiābe",
    "IPA": "m̥ɪǟbə",
    "アラビア文字": "هميب",
    "語根": "hmiV̄",
    "語根+接辞": "hmiV̄-be",
    "同音異義語説明": null,
    "同音異義語+接辞": null,
    "補足": null
  },
  {
    "日本語": "ミズリーク",
    "カラバル語": "mïze-līke",
    "IPA": "mɨd͡zə-lɨ̄kə",
    "アラビア文字": "مز-لك",
    "語根": "mVze-lV̄ke",
    "語根+接辞": "mVze-lV̄ke",
    "同音異義語説明": null,
    "同音異義語+接辞": null,
    "補足": "信徒のことです。"
  },
  {
    "日本語": "～ではない",
    "カラバル語": "moi",
    "IPA": "mɵɪ",
    "アラビア文字": "مي",
    "語根": "moi",
    "語根+接辞": "moi",
    "同音異義語説明": null,
    "同音異義語+接辞": null,
    "補足": null
  },
  {
    "日本語": "多くの",
    "カラバル語": "muàr",
    "IPA": "mʊä̀r",
    "アラビア文字": "مور",
    "語根": "mV̀",
    "語根+接辞": "mV̀-r",
    "同音異義語説明": null,
    "同音異義語+接辞": null,
    "補足": null
  },
  {
    "日本語": "息子/娘",
    "カラバル語": "hna/hne",
    "IPA": "n̥ä/n̥ə",
    "アラビア文字": "هن/هن",
    "語根": "hnV",
    "語根+接辞": "hnV",
    "同音異義語説明": null,
    "同音異義語+接辞": null,
    "補足": null
  },
  {
    "日本語": "砂",
    "カラバル語": "nēul",
    "IPA": "nə̄ʊl",
    "アラビア文字": "نول",
    "語根": "nV̄ul",
    "語根+接辞": "nV̄ul",
    "同音異義語説明": null,
    "同音異義語+接辞": null,
    "補足": null
  },
  {
    "日本語": "世界",
    "カラバル語": "niāfiá",
    "IPA": "nɪǟɸɪä́",
    "アラビア文字": "نيفي",
    "語根": "niV̄fiV́",
    "語根+接辞": "niV̄fiV́",
    "同音異義語説明": null,
    "同音異義語+接辞": null,
    "補足": null
  },
  {
    "日本語": "血",
    "カラバル語": "nuò",
    "IPA": "nʊɵ̀",
    "アラビア文字": "نو",
    "語根": "nuV̀",
    "語根+接辞": "nuV̀",
    "同音異義語説明": null,
    "同音異義語+接辞": null,
    "補足": null
  },
  {
    "日本語": "一緒に",
    "カラバル語": "nuóye",
    "IPA": "nʊɵ́jə",
    "アラビア文字": "نوي",
    "語根": "nuó",
    "語根+接辞": "nuó-ye",
    "同音異義語説明": null,
    "同音異義語+接辞": null,
    "補足": null
  },
  {
    "日本語": "誰が",
    "カラバル語": "pā",
    "IPA": "pǟ",
    "アラビア文字": "پ",
    "語根": "pā",
    "語根+接辞": "pā",
    "同音異義語説明": null,
    "同音異義語+接辞": null,
    "補足": null
  },
  {
    "日本語": "洗う",
    "カラバル語": "pábe",
    "IPA": "pä́bə",
    "アラビア文字": "پب",
    "語根": "pV́",
    "語根+接辞": "pV́-be",
    "同音異義語説明": null,
    "同音異義語+接辞": null,
    "補足": null
  },
  {
    "日本語": "何が",
    "カラバル語": "fāng",
    "IPA": "ɸǟŋ",
    "アラビア文字": "فﯓ",
    "語根": "fāng",
    "語根+接辞": "fāng",
    "同音異義語説明": null,
    "同音異義語+接辞": null,
    "補足": null
  },
  {
    "日本語": "笑う",
    "カラバル語": "fāube",
    "IPA": "ɸǟʊbə",
    "アラビア文字": "فوب",
    "語根": "fV̄u",
    "語根+接辞": "fV̄u-be",
    "同音異義語説明": null,
    "同音異義語+接辞": null,
    "補足": null
  },
  {
    "日本語": "日（暦の）",
    "カラバル語": "fià",
    "IPA": "ɸɪä̀",
    "アラビア文字": "في",
    "語根": "fiV̀",
    "語根+接辞": "fiV̀",
    "同音異義語説明": null,
    "同音異義語+接辞": null,
    "補足": null
  },
  {
    "日本語": "飛ぶ",
    "カラバル語": "fiábe",
    "IPA": "ɸɪä́bə",
    "アラビア文字": "فيب",
    "語根": "fiV́",
    "語根+接辞": "fiV́-be",
    "同音異義語説明": null,
    "同音異義語+接辞": null,
    "補足": null
  },
  {
    "日本語": "人",
    "カラバル語": "píl",
    "IPA": "pɨ́l",
    "アラビア文字": "پل",
    "語根": "pV́l",
    "語根+接辞": "pV́l",
    "同音異義語説明": null,
    "同音異義語+接辞": null,
    "補足": null
  },
  {
    "日本語": "湖",
    "カラバル語": "fïlē",
    "IPA": "ɸɨlə̄",
    "アラビア文字": "فل",
    "語根": "fïlV̄",
    "語根+接辞": "fïlV̄",
    "同音異義語説明": null,
    "同音異義語+接辞": null,
    "補足": null
  },
  {
    "日本語": "背中",
    "カラバル語": "pïliè",
    "IPA": "pɨlɪə̀",
    "アラビア文字": "پلي",
    "語根": "pïliV̀",
    "語根+接辞": "pïliV̀",
    "同音異義語説明": null,
    "同音異義語+接辞": null,
    "補足": null
  },
  {
    "日本語": "肉",
    "カラバル語": "pïlò",
    "IPA": "pɨlɵ̀",
    "アラビア文字": "پل",
    "語根": "pïlV̀",
    "語根+接辞": "pïlV̀",
    "同音異義語説明": null,
    "同音異義語+接辞": null,
    "補足": null
  },
  {
    "日本語": "父",
    "カラバル語": "fïrán",
    "IPA": "ɸɨrä́n",
    "アラビア文字": "فرن",
    "語根": "fïrV́n",
    "語根+接辞": "fïrV́n",
    "同音異義語説明": null,
    "同音異義語+接辞": null,
    "補足": null
  },
  {
    "日本語": 6,
    "カラバル語": "fïrï",
    "IPA": "ɸɨrɨ",
    "アラビア文字": "فر",
    "語根": "fïrï",
    "語根+接辞": "fïrï",
    "同音異義語説明": null,
    "同音異義語+接辞": null,
    "補足": null
  },
  {
    "日本語": "脚",
    "カラバル語": "fïrì",
    "IPA": "ɸɨrɨ̀",
    "アラビア文字": "فر",
    "語根": "fïrV̀",
    "語根+接辞": "fïrV̀",
    "同音異義語説明": null,
    "同音異義語+接辞": null,
    "補足": null
  },
  {
    "日本語": "もしも",
    "カラバル語": "fó",
    "IPA": "ɸɵ́",
    "アラビア文字": "ف",
    "語根": "fó",
    "語根+接辞": "fó",
    "同音異義語説明": null,
    "同音異義語+接辞": null,
    "補足": null
  },
  {
    "日本語": "～さえも",
    "カラバル語": "fōiyei",
    "IPA": "ɸɵ̄ɪjəɪ",
    "アラビア文字": "فييي",
    "語根": "fōiy",
    "語根+接辞": "fōiy-ei",
    "同音異義語説明": null,
    "同音異義語+接辞": null,
    "補足": null
  },
  {
    "日本語": "はい",
    "カラバル語": "qa",
    "IPA": "qä",
    "アラビア文字": "ق",
    "語根": "qa",
    "語根+接辞": "qa",
    "同音異義語説明": null,
    "同音異義語+接辞": null,
    "補足": null
  },
  {
    "日本語": "厚い",
    "カラバル語": "qàr",
    "IPA": "qä̀r",
    "アラビア文字": "قر",
    "語根": "qV̀",
    "語根+接辞": "qV̀-r",
    "同音異義語説明": null,
    "同音異義語+接辞": null,
    "補足": null
  },
  {
    "日本語": "泣く",
    "カラバル語": "qāube",
    "IPA": "qǟʊbə",
    "アラビア文字": "قوب",
    "語根": "qV̄u",
    "語根+接辞": "qV̄u-be",
    "同音異義語説明": null,
    "同音異義語+接辞": null,
    "補足": null
  },
  {
    "日本語": "河岸、湖岸",
    "カラバル語": "qèné",
    "IPA": "qə̀nə́",
    "アラビア文字": "قن",
    "語根": "qV̀né",
    "語根+接辞": "qV̀né",
    "同音異義語説明": null,
    "同音異義語+接辞": null,
    "補足": null
  },
  {
    "日本語": "考える",
    "カラバル語": "qiàbe",
    "IPA": "qɪä̀bə",
    "アラビア文字": "قيب",
    "語根": "qiV̀",
    "語根+接辞": "qiV̀-be",
    "同音異義語説明": null,
    "同音異義語+接辞": null,
    "補足": null
  },
  {
    "日本語": "眼",
    "カラバル語": "qīm",
    "IPA": "qɨ̄m",
    "アラビア文字": "قم",
    "語根": "qV̄m",
    "語根+接辞": "qV̄m",
    "同音異義語説明": null,
    "同音異義語+接辞": null,
    "補足": null
  },
  {
    "日本語": "骨",
    "カラバル語": "qoir",
    "IPA": "qɵɪr",
    "アラビア文字": "قير",
    "語根": "qVir",
    "語根+接辞": "qVir",
    "同音異義語説明": null,
    "同音異義語+接辞": null,
    "補足": null
  },
  {
    "日本語": "白",
    "カラバル語": "quàng",
    "IPA": "qʊä̀ŋ",
    "アラビア文字": "قوﯓ",
    "語根": "quV̀ng",
    "語根+接辞": "quV̀ng",
    "同音異義語説明": null,
    "同音異義語+接辞": null,
    "補足": null
  },
  {
    "日本語": "できる",
    "カラバル語": "hrabe",
    "IPA": "r̥äbə",
    "アラビア文字": "هرب",
    "語根": "hrV",
    "語根+接辞": "hrV-be",
    "同音異義語説明": null,
    "同音異義語+接辞": null,
    "補足": null
  },
  {
    "日本語": "濡れた、湿った",
    "カラバル語": "ghāir",
    "IPA": "ʁǟɪr",
    "アラビア文字": "غير",
    "語根": "ghV̄i",
    "語根+接辞": "ghV̄i-r",
    "同音異義語説明": null,
    "同音異義語+接辞": null,
    "補足": null
  },
  {
    "日本語": "私",
    "カラバル語": "rál",
    "IPA": "rä́l",
    "アラビア文字": "رل",
    "語根": "rV́l",
    "語根+接辞": "rV́l",
    "同音異義語説明": null,
    "同音異義語+接辞": null,
    "補足": null
  },
  {
    "日本語": "我々",
    "カラバル語": "ráleny",
    "IPA": "rä́ləɲ",
    "アラビア文字": "رلڽ",
    "語根": "rV́leny",
    "語根+接辞": "rV́leny",
    "同音異義語説明": null,
    "同音異義語+接辞": null,
    "補足": null
  },
  {
    "日本語": "フラム",
    "カラバル語": "hram",
    "IPA": "r̥äm",
    "アラビア文字": "هرم",
    "語根": "hrVm",
    "語根+接辞": "hrVm",
    "同音異義語説明": null,
    "同音異義語+接辞": null,
    "補足": "禁忌（やってはいけないこと）を指します。"
  },
  {
    "日本語": "村、集落",
    "カラバル語": "rànuá",
    "IPA": "rä̀nʊä́",
    "アラビア文字": "رنو",
    "語根": "rV̀nuV́",
    "語根+接辞": "rV̀nuV́",
    "同音異義語説明": null,
    "同音異義語+接辞": null,
    "補足": null
  },
  {
    "日本語": "月（暦の）",
    "カラバル語": "hraùl",
    "IPA": "r̥äùl",
    "アラビア文字": "هرùل",
    "語根": "hrV̀ul",
    "語根+接辞": "hrV̀ul",
    "同音異義語説明": null,
    "同音異義語+接辞": null,
    "補足": null
  },
  {
    "日本語": "雪",
    "カラバル語": "ghēi",
    "IPA": "ʁə̄ɪ",
    "アラビア文字": "غي",
    "語根": "ghV̄i",
    "語根+接辞": "ghV̄i",
    "同音異義語説明": null,
    "同音異義語+接辞": null,
    "補足": null
  },
  {
    "日本語": "どこ",
    "カラバル語": "ghiā",
    "IPA": "ʁɪǟ",
    "アラビア文字": "غي",
    "語根": "ghiā",
    "語根+接辞": "ghiā",
    "同音異義語説明": null,
    "同音異義語+接辞": null,
    "補足": null
  },
  {
    "日本語": "欲する、望む",
    "カラバル語": "riabe",
    "IPA": "rɪäbə",
    "アラビア文字": "ريب",
    "語根": "riV",
    "語根+接辞": "riV-be",
    "同音異義語説明": null,
    "同音異義語+接辞": null,
    "補足": null
  },
  {
    "日本語": "遊ぶ",
    "カラバル語": "riàbe",
    "IPA": "rɪä̀bə",
    "アラビア文字": "ريب",
    "語根": "riV̀",
    "語根+接辞": "riV̀-be",
    "同音異義語説明": null,
    "同音異義語+接辞": null,
    "補足": null
  },
  {
    "日本語": "理解する",
    "カラバル語": "riàbe",
    "IPA": "rɪä̀bə",
    "アラビア文字": "ريب",
    "語根": "riV̀",
    "語根+接辞": "riV̀-be",
    "同音異義語説明": "「遊ぶ」との区別",
    "同音異義語+接辞": "sè-riV̀-be",
    "補足": null
  },
  {
    "日本語": "信じる",
    "カラバル語": "ghiábe",
    "IPA": "ʁɪä́bə",
    "アラビア文字": "غيب",
    "語根": "ghiV́",
    "語根+接辞": "ghiV́-be",
    "同音異義語説明": null,
    "同音異義語+接辞": null,
    "補足": null
  },
  {
    "日本語": 4,
    "カラバル語": "hrïl",
    "IPA": "r̥ɨl",
    "アラビア文字": "هرل",
    "語根": "hrïl",
    "語根+接辞": "hrïl",
    "同音異義語説明": null,
    "同音異義語+接辞": null,
    "補足": null
  },
  {
    "日本語": "根",
    "カラバル語": "rïn",
    "IPA": "rɨn",
    "アラビア文字": "رن",
    "語根": "rV",
    "語根+接辞": "rV",
    "同音異義語説明": null,
    "同音異義語+接辞": null,
    "補足": null
  },
  {
    "日本語": 1,
    "カラバル語": "ghír",
    "IPA": "ʁɨ́r",
    "アラビア文字": "غر",
    "語根": "ghír",
    "語根+接辞": "ghír",
    "同音異義語説明": null,
    "同音異義語+接辞": null,
    "補足": null
  },
  {
    "日本語": "腕",
    "カラバル語": "ghīun",
    "IPA": "ʁɨ̄ʊn",
    "アラビア文字": "غون",
    "語根": "ghV̄un",
    "語根+接辞": "ghV̄un",
    "同音異義語説明": null,
    "同音異義語+接辞": null,
    "補足": null
  },
  {
    "日本語": "暑い",
    "カラバル語": "hruār",
    "IPA": "r̥ʊǟr",
    "アラビア文字": "هرور",
    "語根": "hruV̄",
    "語根+接辞": "hruV̄-r",
    "同音異義語説明": null,
    "同音異義語+接辞": null,
    "補足": null
  },
  {
    "日本語": "だから、ゆえに",
    "カラバル語": "ruo",
    "IPA": "rʊɵ",
    "アラビア文字": "رو",
    "語根": "ruo",
    "語根+接辞": "ruo",
    "同音異義語説明": null,
    "同音異義語+接辞": null,
    "補足": null
  },
  {
    "日本語": "青",
    "カラバル語": "sà",
    "IPA": "sä̀",
    "アラビア文字": "س",
    "語根": "sV̀",
    "語根+接辞": "sV̀",
    "同音異義語説明": null,
    "同音異義語+接辞": null,
    "補足": null
  },
  {
    "日本語": "サイ",
    "カラバル語": "sài",
    "IPA": "sä̀ɪ",
    "アラビア文字": "سي",
    "語根": "sV̀i",
    "語根+接辞": "sV̀i",
    "同音異義語説明": null,
    "同音異義語+接辞": null,
    "補足": "義務の一つで、学習のことです。"
  },
  {
    "日本語": "知る",
    "カラバル語": "saibe",
    "IPA": "säɪbə",
    "アラビア文字": "سيب",
    "語根": "sVi",
    "語根+接辞": "sVi-be",
    "同音異義語説明": null,
    "同音異義語+接辞": null,
    "補足": null
  },
  {
    "日本語": "サカイ",
    "カラバル語": "saqài",
    "IPA": "säqä̀ɪ",
    "アラビア文字": "سقي",
    "語根": "sVqV̀i",
    "語根+接辞": "sVqV̀i",
    "同音異義語説明": null,
    "同音異義語+接辞": null,
    "補足": "禁忌の一つで、濫用のことです。"
  },
  {
    "日本語": "古い",
    "カラバル語": "sār",
    "IPA": "sǟr",
    "アラビア文字": "سر",
    "語根": "sV̄",
    "語根+接辞": "sV̄-r",
    "同音異義語説明": null,
    "同音異義語+接辞": null,
    "補足": null
  },
  {
    "日本語": "サール",
    "カラバル語": "sār",
    "IPA": "sǟr",
    "アラビア文字": "سر",
    "語根": "sV̄r",
    "語根+接辞": "sV̄r",
    "同音異義語説明": null,
    "同音異義語+接辞": null,
    "補足": "義務の一つで、実践のことです。"
  },
  {
    "日本語": "手に取る",
    "カラバル語": "sàube",
    "IPA": "sä̀ʊbə",
    "アラビア文字": "سوب",
    "語根": "sV̀u",
    "語根+接辞": "sV̀u-be",
    "同音異義語説明": null,
    "同音異義語+接辞": null,
    "補足": null
  },
  {
    "日本語": "セデュール",
    "カラバル語": "sèduīl",
    "IPA": "sə̀dʊɨ̄l",
    "アラビア文字": "سدول",
    "語根": "duV̄l",
    "語根+接辞": "sèduV̄l",
    "同音異義語説明": null,
    "同音異義語+接辞": null,
    "補足": "礼拝における五体投地です。"
  },
  {
    "日本語": "セガキア",
    "カラバル語": "sègakiá",
    "IPA": "sə̀gäkɪä́",
    "アラビア文字": "سگكي",
    "語根": "gVkiV́",
    "語根+接辞": "sè-gVkiV́",
    "同音異義語説明": null,
    "同音異義語+接辞": null,
    "補足": "断食明けに行われる大施食会（炊き出し）のことです。"
  },
  {
    "日本語": "とても",
    "カラバル語": "soye",
    "IPA": "sɵjə",
    "アラビア文字": "سي",
    "語根": "so",
    "語根+接辞": "so-ye",
    "同音異義語説明": null,
    "同音異義語+接辞": null,
    "補足": null
  },
  {
    "日本語": "タアル",
    "カラバル語": "tahàl",
    "IPA": "täɦä̀l",
    "アラビア文字": "تعل",
    "語根": "tVhV̀l",
    "語根+接辞": "tVhV̀l",
    "同音異義語説明": null,
    "同音異義語+接辞": null,
    "補足": "義務の一つで、清浄のことです。"
  },
  {
    "日本語": "話す",
    "カラバル語": "táibe",
    "IPA": "tä́ɪbə",
    "アラビア文字": "تيب",
    "語根": "tV́i",
    "語根+接辞": "tV́i-be",
    "同音異義語説明": null,
    "同音異義語+接辞": null,
    "補足": null
  },
  {
    "日本語": "ターキア",
    "カラバル語": "tākiá",
    "IPA": "tǟkɪä́",
    "アラビア文字": "تكي",
    "語根": "tV̄kiV́",
    "語根+接辞": "tV̄kiV́",
    "同音異義語説明": null,
    "同音異義語+接辞": null,
    "補足": "露店のことです。"
  },
  {
    "日本語": "貯金",
    "カラバル語": "tamāl",
    "IPA": "tämǟl",
    "アラビア文字": "تمل",
    "語根": "tVmV̄l",
    "語根+接辞": "tamV̄l",
    "同音異義語説明": null,
    "同音異義語+接辞": null,
    "補足": null
  },
  {
    "日本語": "走る",
    "カラバル語": "tàrïbe",
    "IPA": "tä̀rɨbə",
    "アラビア文字": "ترب",
    "語根": "tV̀rV",
    "語根+接辞": "tV̀rV-be",
    "同音異義語説明": null,
    "同音異義語+接辞": null,
    "補足": null
  },
  {
    "日本語": "行く",
    "カラバル語": "chábe",
    "IPA": "t͡ɕä́bə",
    "アラビア文字": "چب",
    "語根": "chV́",
    "語根+接辞": "chV́-be",
    "同音異義語説明": null,
    "同音異義語+接辞": null,
    "補足": null
  },
  {
    "日本語": "緑",
    "カラバル語": "chāi",
    "IPA": "t͡ɕǟɪ",
    "アラビア文字": "چي",
    "語根": "chV̄i",
    "語根+接辞": "chV̄i",
    "同音異義語説明": null,
    "同音異義語+接辞": null,
    "補足": null
  },
  {
    "日本語": "チャール",
    "カラバル語": "chāl",
    "IPA": "t͡ɕǟl",
    "アラビア文字": "چل",
    "語根": "chV̄l",
    "語根+接辞": "chV̄l",
    "同音異義語説明": null,
    "同音異義語+接辞": null,
    "補足": "禁忌の一つで、悪句のことです。"
  },
  {
    "日本語": "心、心臓",
    "カラバル語": "chuē",
    "IPA": "t͡ɕʊə̄",
    "アラビア文字": "چو",
    "語根": "chuV̄",
    "語根+接辞": "chuV̄",
    "同音異義語説明": null,
    "同音異義語+接辞": null,
    "補足": null
  },
  {
    "日本語": "木",
    "カラバル語": "té",
    "IPA": "tə́",
    "アラビア文字": "ت",
    "語根": "tV́",
    "語根+接辞": "tV́",
    "同音異義語説明": null,
    "同音異義語+接辞": null,
    "補足": null
  },
  {
    "日本語": 8,
    "カラバル語": "tï",
    "IPA": "tɨ",
    "アラビア文字": "ت",
    "語根": "tï",
    "語根+接辞": "tï",
    "同音異義語説明": null,
    "同音異義語+接辞": null,
    "補足": null
  },
  {
    "日本語": "森",
    "カラバル語": "tī",
    "IPA": "tɨ̄",
    "アラビア文字": "ت",
    "語根": "tV̄",
    "語根+接辞": "tV̄",
    "同音異義語説明": null,
    "同音異義語+接辞": null,
    "補足": null
  },
  {
    "日本語": "女王",
    "カラバル語": "tïléine",
    "IPA": "tɨlə́ɪnə",
    "アラビア文字": "تلين",
    "語根": "tïlV́ine",
    "語根+接辞": "tïlV́ine",
    "同音異義語説明": null,
    "同音異義語+接辞": null,
    "補足": null
  },
  {
    "日本語": "川",
    "カラバル語": "tïlèu",
    "IPA": "tɨlə̀ʊ",
    "アラビア文字": "تلو",
    "語根": "tïlV̀u",
    "語根+接辞": "tïlV̀u",
    "同音異義語説明": null,
    "同音異義語+接辞": null,
    "補足": null
  },
  {
    "日本語": "花",
    "カラバル語": "tïlí",
    "IPA": "tɨlɨ́",
    "アラビア文字": "تل",
    "語根": "tïlV́",
    "語根+接辞": "tïlV́",
    "同音異義語説明": null,
    "同音異義語+接辞": null,
    "補足": null
  },
  {
    "日本語": "耳",
    "カラバル語": "tïlìghe",
    "IPA": "tɨlɨ̀ʁə",
    "アラビア文字": "تلغ",
    "語根": "tïlV̀ghe",
    "語根+接辞": "tïlV̀ghe",
    "同音異義語説明": null,
    "同音異義語+接辞": null,
    "補足": null
  },
  {
    "日本語": 100,
    "カラバル語": "tïnïu",
    "IPA": "tɨnɨʊ",
    "アラビア文字": "تنو",
    "語根": "tïnïu",
    "語根+接辞": "tïnïu",
    "同音異義語説明": null,
    "同音異義語+接辞": null,
    "補足": null
  },
  {
    "日本語": "奪う",
    "カラバル語": "tïnuábe",
    "IPA": "tɨnʊä́bə",
    "アラビア文字": "تنوب",
    "語根": "tVnuV́",
    "語根+接辞": "tVnuV́-be",
    "同音異義語説明": null,
    "同音異義語+接辞": null,
    "補足": null
  },
  {
    "日本語": "鳥",
    "カラバル語": "tïrïu",
    "IPA": "tɨrɨʊ",
    "アラビア文字": "ترو",
    "語根": "tïrVu",
    "語根+接辞": "tïrVu",
    "同音異義語説明": null,
    "同音異義語+接辞": null,
    "補足": null
  },
  {
    "日本語": "顔",
    "カラバル語": "cïlēl",
    "IPA": "t͡sɨlə̄l",
    "アラビア文字": "ڃلل",
    "語根": "cïlV̄l",
    "語根+接辞": "cïlV̄l",
    "同音異義語説明": null,
    "同音異義語+接辞": null,
    "補足": null
  },
  {
    "日本語": 5,
    "カラバル語": "cïlíl",
    "IPA": "t͡sɨlɨ́l",
    "アラビア文字": "ڃلل",
    "語根": "cïlíl",
    "語根+接辞": "cïlíl",
    "同音異義語説明": null,
    "同音異義語+接辞": null,
    "補足": null
  },
  {
    "日本語": "卵",
    "カラバル語": "cīr",
    "IPA": "t͡sɨ̄r",
    "アラビア文字": "ڃر",
    "語根": "cV̄r",
    "語根+接辞": "cV̄r",
    "同音異義語説明": null,
    "同音異義語+接辞": null,
    "補足": null
  },
  {
    "日本語": "国",
    "カラバル語": "cīxál",
    "IPA": "t͡sɨ̄χä́l",
    "アラビア文字": "ڃخل",
    "語根": "cīxV́l",
    "語根+接辞": "cīxV́l",
    "同音異義語説明": null,
    "同音異義語+接辞": null,
    "補足": null
  },
  {
    "日本語": "子供（血縁上の）",
    "カラバル語": "cuá",
    "IPA": "t͡sʊä́",
    "アラビア文字": "ڃو",
    "語根": "cuV́",
    "語根+接辞": "cuV́",
    "同音異義語説明": null,
    "同音異義語+接辞": null,
    "補足": null
  },
  {
    "日本語": "寒い",
    "カラバル語": "tuàr",
    "IPA": "tʊä̀r",
    "アラビア文字": "تور",
    "語根": "tuV̀",
    "語根+接辞": "tuV̀-r",
    "同音異義語説明": null,
    "同音異義語+接辞": null,
    "補足": null
  },
  {
    "日本語": "種",
    "カラバル語": "vá",
    "IPA": "βä́",
    "アラビア文字": "ڤ",
    "語根": "vV́",
    "語根+接辞": "vV́",
    "同音異義語説明": null,
    "同音異義語+接辞": null,
    "補足": null
  },
  {
    "日本語": "置く",
    "カラバル語": "vabe",
    "IPA": "βäbə",
    "アラビア文字": "ڤب",
    "語根": "vV",
    "語根+接辞": "vV-be",
    "同音異義語説明": null,
    "同音異義語+接辞": null,
    "補足": null
  },
  {
    "日本語": "怒る",
    "カラバル語": "vàibe",
    "IPA": "βä̀ɪbə",
    "アラビア文字": "ڤيب",
    "語根": "vV̀i",
    "語根+接辞": "vV̀i-be",
    "同音異義語説明": null,
    "同音異義語+接辞": null,
    "補足": null
  },
  {
    "日本語": "あれ（遠くのもの）",
    "カラバル語": "vï",
    "IPA": "βɨ",
    "アラビア文字": "ڤ",
    "語根": "vV",
    "語根+接辞": "vV",
    "同音異義語説明": null,
    "同音異義語+接辞": null,
    "補足": null
  },
  {
    "日本語": "道",
    "カラバル語": "vï",
    "IPA": "βɨ",
    "アラビア文字": "ڤ",
    "語根": "vV",
    "語根+接辞": "vV",
    "同音異義語説明": "「あれ」との区別",
    "同音異義語+接辞": "sè-vï",
    "補足": null
  },
  {
    "日本語": "剣",
    "カラバル語": "ví",
    "IPA": "βɨ́",
    "アラビア文字": "ڤ",
    "語根": "vV́",
    "語根+接辞": "vV́",
    "同音異義語説明": null,
    "同音異義語+接辞": null,
    "補足": null
  },
  {
    "日本語": "歌",
    "カラバル語": "vìl",
    "IPA": "βɨ̀l",
    "アラビア文字": "ڤل",
    "語根": "vV̀l",
    "語根+接辞": "vV̀l",
    "同音異義語説明": null,
    "同音異義語+接辞": null,
    "補足": null
  },
  {
    "日本語": "殺す",
    "カラバル語": "vuàbe",
    "IPA": "βʊä̀bə",
    "アラビア文字": "ڤوب",
    "語根": "vuV̀",
    "語根+接辞": "vuV̀-be",
    "同音異義語説明": null,
    "同音異義語+接辞": null,
    "補足": null
  },
  {
    "日本語": "少しの",
    "カラバル語": "vuàchár",
    "IPA": "βʊä̀t͡ɕä́r",
    "アラビア文字": "ڤوچر",
    "語根": "vuV̀che",
    "語根+接辞": "vuV̀chá-r",
    "同音異義語説明": null,
    "同音異義語+接辞": null,
    "補足": null
  },
  {
    "日本語": "生きる",
    "カラバル語": "xaibe",
    "IPA": "χäɪbə",
    "アラビア文字": "خيب",
    "語根": "xVi",
    "語根+接辞": "xVi-be",
    "同音異義語説明": null,
    "同音異義語+接辞": null,
    "補足": null
  },
  {
    "日本語": "民族",
    "カラバル語": "xàuzuā",
    "IPA": "χä̀ʊd͡zʊǟ",
    "アラビア文字": "خوزو",
    "語根": "xV̀uzuV̄",
    "語根+接辞": "xV̀uzuV̄",
    "同音異義語説明": null,
    "同音異義語+接辞": null,
    "補足": null
  },
  {
    "日本語": "炎",
    "カラバル語": "xèiny",
    "IPA": "χə̀ɪɲ",
    "アラビア文字": "خيڽ",
    "語根": "xV̀iny",
    "語根+接辞": "xV̀iny",
    "同音異義語説明": null,
    "同音異義語+接辞": null,
    "補足": null
  },
  {
    "日本語": "谷",
    "カラバル語": "xīu",
    "IPA": "χɨ̄ʊ",
    "アラビア文字": "خو",
    "語根": "xV̄u",
    "語根+接辞": "xV̄u",
    "同音異義語説明": null,
    "同音異義語+接辞": null,
    "補足": null
  },
  {
    "日本語": "投げる",
    "カラバル語": "xuabe",
    "IPA": "χʊäbə",
    "アラビア文字": "خوب",
    "語根": "xuV",
    "語根+接辞": "xuV-be",
    "同音異義語説明": null,
    "同音異義語+接辞": null,
    "補足": null
  },
  {
    "日本語": "燃やす",
    "カラバル語": "xuabe",
    "IPA": "χʊäbə",
    "アラビア文字": "خوب",
    "語根": "xuV",
    "語根+接辞": "xuV-be",
    "同音異義語説明": "「投げる」との区別",
    "同音異義語+接辞": "sè-xuV-be",
    "補足": null
  }
]